LICENSE
README.md
pyproject.toml
polarisx/__init__.py
polarisx/catalog.py
polarisx/rest_client.py
pyspark_polarisx_test-0.1.4.dist-info/METADATA
pyspark_polarisx_test-0.1.4.dist-info/WHEEL
pyspark_polarisx_test-0.1.4.dist-info/licenses/LICENSE
pyspark_polarisx_test-0.1.4.dist-info/RECORD
