Metadata-Version: 2.4
Name: pyspark-polarisx-test
Version: 0.1.4
Summary: Test Polaris Catalog Lib implementation with PySpark
Project-URL: homepage, https://github.com/Carlbrr/Polaris_PySpark
Author-email: Carl Bruun <carl99@live.dk>, Andreas Kongstad <andreaskongstad99@icloud.com>
License: MIT
License-File: LICENSE
Requires-Python: >=3.13
Requires-Dist: pyspark>=3.5.4
Requires-Dist: pytest>=8.3.4
Requires-Dist: requests>=2.32.3
